thds/core/__init__.py
thds/core/ansi_esc.py
thds/core/cache.py
thds/core/calgitver.py
thds/core/cm.py
thds/core/concurrency.py
thds/core/config.py
thds/core/cpus.py
thds/core/decos.py
thds/core/dict_utils.py
thds/core/dump_stacks.py
thds/core/env.py
thds/core/exit_after.py
thds/core/files.py
thds/core/fp.py
thds/core/fretry.py
thds/core/futures.py
thds/core/generators.py
thds/core/git.py
thds/core/hash_cache.py
thds/core/hashing.py
thds/core/home.py
thds/core/hostname.py
thds/core/imports.py
thds/core/inspect.py
thds/core/iterators.py
thds/core/lazy.py
thds/core/link.py
thds/core/logical_root.py
thds/core/merge_args.py
thds/core/meta.py
thds/core/parallel.py
thds/core/partition.py
thds/core/pickle_visit.py
thds/core/prof.py
thds/core/progress.py
thds/core/project_root.py
thds/core/protocols.py
thds/core/py.typed
thds/core/refcount.py
thds/core/scaling.py
thds/core/scope.py
thds/core/source_serde.py
thds/core/stack_context.py
thds/core/thread_debug.py
thds/core/thunks.py
thds/core/timer.py
thds/core/tmp.py
thds/core/types.py
thds/core/uri_assign.py
thds/core/log/__init__.py
thds/core/log/basic_config.py
thds/core/log/json_formatter.py
thds/core/log/kw_formatter.py
thds/core/log/kw_logger.py
thds/core/log/logfmt.py
thds/core/source/__init__.py
thds/core/source/_construct.py
thds/core/source/_construct_tree.py
thds/core/source/_download.py
thds/core/source/_upload.py
thds/core/source/serde.py
thds/core/source/src.py
thds/core/source/tree.py
thds/core/sqlite/__init__.py
thds/core/sqlite/connect.py
thds/core/sqlite/copy.py
thds/core/sqlite/ddl.py
thds/core/sqlite/functions.py
thds/core/sqlite/index.py
thds/core/sqlite/insert_utils.py
thds/core/sqlite/merge.py
thds/core/sqlite/meta.py
thds/core/sqlite/read.py
thds/core/sqlite/sqlmap.py
thds/core/sqlite/structured.py
thds/core/sqlite/types.py
thds/core/sqlite/upsert.py
thds/core/sqlite/write.py
thds_core-1.50.20260130200327.dist-info/METADATA
thds_core-1.50.20260130200327.dist-info/WHEEL
thds_core-1.50.20260130200327.dist-info/entry_points.txt
thds_core-1.50.20260130200327.dist-info/top_level.txt
thds_core-1.50.20260130200327.dist-info/RECORD
