Metadata-Version: 2.4
Name: thds.core
Version: 1.50.20260130200327
Summary: Core utilities.
Author-email: Trilliant Health <info@trillianthealth.com>
License: MIT
Project-URL: Repository, https://github.com/TrilliantHealth/trilliant-data-science
Requires-Python: >=3.9
Requires-Dist: setuptools
Requires-Dist: typing-extensions
